raytoolsbox/__init__.py
raytoolsbox/crypto_manager.py
raytoolsbox/mailToPhone.py
raytoolsbox/to_github.py
raytoolsbox/useful_func.py
raytoolsbox-1.0.0.dist-info/METADATA
raytoolsbox-1.0.0.dist-info/WHEEL
raytoolsbox-1.0.0.dist-info/top_level.txt
raytoolsbox-1.0.0.dist-info/RECORD
