Metadata-Version: 2.4
Name: raytoolsbox
Version: 1.0.0
Summary: Add your description here
Author: TIMLES@https://github.com/TIMLES
License: MIT
Requires-Python: >=3.13
Requires-Dist: cryptography>=46.0.4
Requires-Dist: keyring>=25.7.0
Requires-Dist: pyyaml>=6.0.3
Requires-Dist: requests>=2.32.5
